cuda_symreg/__init__.py
cuda_symreg/core.py
cuda_symreg/lib/libgasymreg.so
cuda_symreg-0.1.2.dist-info/METADATA
cuda_symreg-0.1.2.dist-info/WHEEL
cuda_symreg-0.1.2.dist-info/top_level.txt
cuda_symreg-0.1.2.dist-info/RECORD
