Metadata-Version: 2.4
Name: cuda_symreg
Version: 0.1.2
Summary: Regresión Simbólica con CUDA
Author-email: Ariel Lisímaco Pincay Pérez <arielpincay812@gmail.com>
Requires-Python: >=3.8
Requires-Dist: numpy>=1.20.0
